wpa/__init__.py
wpa/functions.py
wpa/visualize.py
WhatsappInspect-1.0.5.dist-info/METADATA
WhatsappInspect-1.0.5.dist-info/WHEEL
WhatsappInspect-1.0.5.dist-info/top_level.txt
WhatsappInspect-1.0.5.dist-info/RECORD
