Metadata-Version: 2.1
Name: WhatsappInspect
Version: 1.0.5
Summary: A simple package for letting user to track and analyze all the exported whatsapp chat data for differnt usage
Home-page: UNKNOWN
Author: Anindyadeep Sannigrahi
Author-email: proanindyadeep@gmail.com
License: UNKNOWN
Keywords: python,pandas,data,EDA,data analysis,whatsapp
Platform: UNKNOWN
Classifier: Development Status :: 1 - Planning
Classifier: Intended Audience :: Developers
Classifier: Programming Language :: Python :: 3
Classifier: Operating System :: Unix
Classifier: Operating System :: MacOS :: MacOS X
Classifier: Operating System :: Microsoft :: Windows
Requires-Dist: certifi (==2021.5.30)
Requires-Dist: cycler (==0.10.0)
Requires-Dist: demoji (==1.1.0)
Requires-Dist: emoji (==1.4.2)
Requires-Dist: importlib-resources (==5.2.2)
Requires-Dist: kiwisolver (==1.3.1)
Requires-Dist: matplotlib (==3.3.4)
Requires-Dist: numpy (==1.19.5)
Requires-Dist: pandas (==1.1.5)
Requires-Dist: Pillow (==8.3.2)
Requires-Dist: plotly (==5.3.1)
Requires-Dist: pyparsing (==2.4.7)
Requires-Dist: python-dateutil (==2.8.2)
Requires-Dist: pytz (==2021.1)
Requires-Dist: scipy (==1.5.4)
Requires-Dist: seaborn (==0.11.2)
Requires-Dist: six (==1.16.0)
Requires-Dist: tabulate (==0.8.9)
Requires-Dist: tenacity (==8.0.1)
Requires-Dist: wordcloud (==1.8.1)
Requires-Dist: zipp (==3.5.0)
